README.md
androidact.py
setup.py
androidact.egg-info/PKG-INFO
androidact.egg-info/SOURCES.txt
androidact.egg-info/dependency_links.txt
androidact.egg-info/entry_points.txt
androidact.egg-info/requires.txt
androidact.egg-info/top_level.txt