Metadata-Version: 1.0
Name: androidact
Version: 0.1
Summary: Android CLI Tools
Home-page: https://github.com/bvdaakster/act
Author: Bas van den Aakster
Author-email: UNKNOWN
License: UNKNOWN
Platform: UNKNOWN
